{
  "indexes": [
    {
      "collectionGroup": "copart_vehicles",
      "queryScope": "COLLECTION",
      "fields": [
        {
          "fieldPath": "make",
          "order": "ASCENDING"
        },
        {
          "fieldPath": "model",
          "order": "ASCENDING"
        },
        {
          "fieldPath": "year",
          "order": "DESCENDING"
        }
      ]
    },
    {
      "collectionGroup": "copart_vehicles",
      "queryScope": "COLLECTION",
      "fields": [
        {
          "fieldPath": "make",
          "order": "ASCENDING"
        },
        {
          "fieldPath": "updated_at",
          "order": "DESCENDING"
        }
      ]
    },
    {
      "collectionGroup": "copart_vehicles",
      "queryScope": "COLLECTION",
      "fields": [
        {
          "fieldPath": "sale_status",
          "order": "ASCENDING"
        },
        {
          "fieldPath": "updated_at",
          "order": "DESCENDING"
        }
      ]
    },
    {
      "collectionGroup": "search_history",
      "queryScope": "COLLECTION",
      "fields": [
        {
          "fieldPath": "created_at",
          "order": "DESCENDING"
        },
        {
          "fieldPath": "success",
          "order": "ASCENDING"
        }
      ]
    },
    {
      "collectionGroup": "api_requests",
      "queryScope": "COLLECTION",
      "fields": [
        {
          "fieldPath": "created_at",
          "order": "DESCENDING"
        },
        {
          "fieldPath": "status_code",
          "order": "ASCENDING"
        }
      ]
    }
  ],
  "fieldOverrides": []
}
